{
    "0":{
        "bill_id": "xxxxxxx0",
        "date": "20 April 2019",
        "branch": "Quang Trung",
        "used_services": [
            {"name": "nails,tattoo", "price": "20e"},
            {"name": "nails", "price": "20e"}
        ],
        "bought_products":{
            "0":{
                "name": "OPI orange", 
                "quantity": "2", 
                "price": "20e"
            },
            "1":{
                "name": "OPI orange", 
                "quantity": "2", 
                "price": "20e"
            }
        },
        "staff": "Dai Thu Trang"
    },
    "1":{
        "bill_id": "xxxxxxx1",
            "date": "20 April 2019",
            "branch": "Quang Trung",
            "used_services": [
                {"name": "nails,tattoo", "price": "20e"},
                {"name": "nails", "price": "20e"}
            ],
            "bought_products":[
                {"name": "OPI orange", "quantity": "2", "price": "20e"},
                {"name": "OPI orange", "quantity": "2", "price": "20e"}  
            ],
            "staff": "Dai Thu Trang"
    },
    "2":{
        "bill_id": "xxxxxxx1",
            "date": "20 April 2019",
            "branch": "Quang Trung",
            "used_services": [
                {"name": "nails,tattoo", "price": "20e"},
                {"name": "nails", "price": "20e"}
            ],
            "bought_products":[
                {"name": "OPI orange", "quantity": "2", "price": "20e"},
                {"name": "OPI orange", "quantity": "2", "price": "20e"}  
            ],
            "staff": "Dai Thu Trang"
    }


}